CHANGES.txt
LICENSE.txt
MANIFEST.in
README.rst
setup.cfg
setup.py
multirange/__init__.py
multirange.egg-info/PKG-INFO
multirange.egg-info/SOURCES.txt
multirange.egg-info/dependency_links.txt
multirange.egg-info/top_level.txt
tests/__init__.py
tests/test_most.py