Metadata-Version: 1.1
Name: multirange
Version: 0.2.0
Summary: Convenience functions for multiple range-like objects
Home-page: https://github.com/iburadempa/multirange
Author: ibu radempa
Author-email: ibu@radempa.de
License: MIT
Keywords: set integer integers range ranges multiple span interval operations
Platform: UNKNOWN
Classifier: Development Status :: 3 - Alpha
Classifier: Intended Audience :: Developers
Classifier: Intended Audience :: Science/Research
Classifier: Topic :: Software Development :: Libraries :: Python Modules
Classifier: Topic :: Utilities
Classifier: License :: OSI Approved :: MIT License
Classifier: Programming Language :: Python :: 3.3
Classifier: Programming Language :: Python :: 3.4
